.codecov.yml
.gitignore
.travis.yml
LICENSE
MANIFEST.in
README.md
meta.yaml
post-link.sh
setup.cfg
setup.py
.github/workflows/codeql-analysis.yml
cg2at/__init__.py
cg2at.egg-info/PKG-INFO
cg2at.egg-info/SOURCES.txt
cg2at.egg-info/dependency_links.txt
cg2at.egg-info/entry_points.txt
cg2at.egg-info/not-zip-safe
cg2at.egg-info/requires.txt
cg2at.egg-info/top_level.txt
cg2at/bin/__init__.py
cg2at/bin/at_mod.py
cg2at/bin/at_mod_np.py
cg2at/bin/at_mod_p.py
cg2at/bin/cg2at.py
cg2at/bin/check_library.py
cg2at/bin/g_var.py
cg2at/bin/gen.py
cg2at/bin/gro.py
cg2at/bin/read_in.py
cg2at/forcefields/amber14_lipid17_will_be_removed.ff/Makefile.am
cg2at/forcefields/amber14_lipid17_will_be_removed.ff/Makefile.in
cg2at/forcefields/amber14_lipid17_will_be_removed.ff/aminoacids.arn
cg2at/forcefields/amber14_lipid17_will_be_removed.ff/aminoacids.c.tdb
cg2at/forcefields/amber14_lipid17_will_be_removed.ff/aminoacids.hdb
cg2at/forcefields/amber14_lipid17_will_be_removed.ff/aminoacids.n.tdb
cg2at/forcefields/amber14_lipid17_will_be_removed.ff/aminoacids.r2b
cg2at/forcefields/amber14_lipid17_will_be_removed.ff/aminoacids.rtp
cg2at/forcefields/amber14_lipid17_will_be_removed.ff/aminoacids.vsd
cg2at/forcefields/amber14_lipid17_will_be_removed.ff/atomtypes.atp
cg2at/forcefields/amber14_lipid17_will_be_removed.ff/dna.arn
cg2at/forcefields/amber14_lipid17_will_be_removed.ff/dna.hdb
cg2at/forcefields/amber14_lipid17_will_be_removed.ff/dna.r2b
cg2at/forcefields/amber14_lipid17_will_be_removed.ff/dna.rtp
cg2at/forcefields/amber14_lipid17_will_be_removed.ff/ffbonded.itp
cg2at/forcefields/amber14_lipid17_will_be_removed.ff/ffnonbonded.itp
cg2at/forcefields/amber14_lipid17_will_be_removed.ff/forcefield.doc
cg2at/forcefields/amber14_lipid17_will_be_removed.ff/forcefield.itp
cg2at/forcefields/amber14_lipid17_will_be_removed.ff/gbsa.itp
cg2at/forcefields/amber14_lipid17_will_be_removed.ff/ions.itp
cg2at/forcefields/amber14_lipid17_will_be_removed.ff/lipids.rtp
cg2at/forcefields/amber14_lipid17_will_be_removed.ff/rna.arn
cg2at/forcefields/amber14_lipid17_will_be_removed.ff/rna.hdb
cg2at/forcefields/amber14_lipid17_will_be_removed.ff/rna.r2b
cg2at/forcefields/amber14_lipid17_will_be_removed.ff/rna.rtp
