Metadata-Version: 1.0
Name: cg2at
Version: 2022.6.30
Summary: Converts CG representation into an atomistic representation
Home-page: https://github.com/Aunity/cg2at
Author: owenvickery, Aunity
Author-email: maohuay@hotmail.com
License: GPL-3.0 License
Keywords: CG
Platform: UNKNOWN
